_temp/fix_json.py
toolsman/__init__.py
toolsman/p1.py
toolsman/_examples/create_file.py
toolsman/core/__init__.py
toolsman/core/funcs.py
toolsman/core/log.py
toolsman/core/pools.py
toolsman/core/pools2.py
toolsman/core/wraps.py
toolsman/db/__init__.py
toolsman/db/mysql.py
toolsman/db/test_mysql.py
toolsman/thread_pool/__init__.py
toolsman/thread_pool/thread_pool.py
toolsman-0.0.6.dist-info/METADATA
toolsman-0.0.6.dist-info/WHEEL
toolsman-0.0.6.dist-info/top_level.txt
toolsman-0.0.6.dist-info/RECORD
