Metadata-Version: 2.4
Name: toolsman
Version: 0.0.6
Summary: Python Useful Tools
Author-email: wauo <markadc@126.com>
License-Expression: MIT
Requires-Python: >=3.10
Requires-Dist: loguru
